[
  {
    "fields": {
      "nombres": "Lopez Rodriguez",
      "fecha_ingreso": "2012-10-25",
      "sexo": 0,
      "apellidos": "José Rafael",
      "cedula": "V-12345678"
    },
    "model": "sgt.perito",
    "pk": 1
  },
  {
    "fields": {
      "nombres": "Carlos Miguel",
      "fecha_ingreso": "2011-12-07",
      "sexo": 0,
      "apellidos": "Garcia Ramirez",
      "cedula": "V-87654321"
    },
    "model": "sgt.perito",
    "pk": 2
  },
  {
    "fields": {
      "nombres": "Maria Josefina",
      "fecha_ingreso": "2009-09-25",
      "sexo": 1,
      "apellidos": "Castro Palacios",
      "cedula": "V-12070651"
    },
    "model": "sgt.perito",
    "pk": 3
  },
  {
    "fields": {
      "nombres": "Carmen Josefina",
      "fecha_ingreso": "2012-12-13",
      "sexo": 1,
      "apellidos": "Guzman",
      "cedula": "E-14321427"
    },
    "model": "sgt.perito",
    "pk": 4
  },
  {
    "fields": {
      "nombres": "Jorge Luis",
      "fecha_ingreso": "2012-08-15",
      "sexo": 0,
      "apellidos": "Ruiz Camacho",
      "cedula": "E-156876808"
    },
    "model": "sgt.perito",
    "pk": 5
  },
  {
    "fields": {
      "nombres": "Maria Alejandra",
      "fecha_ingreso": "2010-10-14",
      "sexo": 1,
      "apellidos": "del Valle",
      "cedula": "V-12755443"
    },
    "model": "sgt.perito",
    "pk": 6
  },
  {
    "fields": {
      "nombres": "Gabriela Carolina",
      "fecha_ingreso": "2009-10-22",
      "sexo": 1,
      "apellidos": "Correa Lozano",
      "cedula": "V-11545333"
    },
    "model": "sgt.perito",
    "pk": 7
  },
  {
    "fields": {
      "nombres": "Jose Miguel",
      "fecha_ingreso": "2007-12-18",
      "sexo": 0,
      "apellidos": "Varela Rivero",
      "cedula": "V-13233221"
    },
    "model": "sgt.perito",
    "pk": 8
  },
  {
    "fields": {
      "nombres": "Jose Vicente",
      "fecha_ingreso": "2012-09-11",
      "sexo": 0,
      "apellidos": "del Toro",
      "cedula": "E-17443200"
    },
    "model": "sgt.perito",
    "pk": 9
  },
  {
    "fields": {
      "nombres": "Andreina",
      "fecha_ingreso": "2009-09-30",
      "sexo": 1,
      "apellidos": "Gonzalez Sosa",
      "cedula": "V-11321255"
    },
    "model": "sgt.perito",
    "pk": 10
  },
  {
    "fields": {
      "nombres": "Luisa Alejandra",
      "fecha_ingreso": "2008-08-16",
      "sexo": 1,
      "apellidos": "Dos Santos",
      "cedula": "V-10233211"
    },
    "model": "sgt.perito",
    "pk": 11
  },
  {
    "fields": {
      "nombres": "Pedro Gutierrez",
      "fecha_ingreso": "2012-10-17",
      "sexo": 0,
      "apellidos": "Perez Maldonado",
      "cedula": "V-7322123"
    },
    "model": "sgt.perito",
    "pk": 12
  },
  {
    "fields": {
      "nombres": "Eduardo Ramon",
      "fecha_ingreso": "2009-10-13",
      "sexo": 0,
      "apellidos": "Castro Lopez",
      "cedula": "V-10223455"
    },
    "model": "sgt.perito",
    "pk": 13
  },
  {
    "fields": {
      "nombres": "Juan Daniel",
      "fecha_ingreso": "2010-11-24",
      "sexo": 0,
      "apellidos": "Diaz Tovar",
      "cedula": "V-12321233"
    },
    "model": "sgt.perito",
    "pk": 14
  },
  {
    "fields": {
      "nombres": "Patricia",
      "fecha_ingreso": "2006-10-11",
      "sexo": 1,
      "apellidos": "Molina de la Cruz",
      "cedula": "V-8213543"
    },
    "model": "sgt.perito",
    "pk": 15
  },
  {
    "fields": {
      "nombres": "David",
      "fecha_ingreso": "2012-08-23",
      "sexo": 0,
      "apellidos": "Romero Gonzales",
      "cedula": "E-7222113"
    },
    "model": "sgt.perito",
    "pk": 16
  },
  {
    "fields": {
      "nombres": "Hector Manuel",
      "fecha_ingreso": "2011-11-15",
      "sexo": 0,
      "apellidos": "Sanchez Cordovez",
      "cedula": "V-14442123"
    },
    "model": "sgt.perito",
    "pk": 17
  },
  {
    "fields": {
      "nombres": "Juan Gabriel",
      "fecha_ingreso": "2009-10-28",
      "sexo": 0,
      "apellidos": "Millan Flores",
      "cedula": "V-13447532"
    },
    "model": "sgt.perito",
    "pk": 18
  },
  {
    "fields": {
      "nombres": "Cesar Miguel",
      "fecha_ingreso": "2012-06-13",
      "sexo": 0,
      "apellidos": "Mendoza Torrez",
      "cedula": "V-11234311"
    },
    "model": "sgt.perito",
    "pk": 19
  },
  {
    "fields": {
      "nombres": "Elizabeth",
      "fecha_ingreso": "2012-06-14",
      "sexo": 1,
      "apellidos": "Machado Rincon",
      "cedula": "V-8332190"
    },
    "model": "sgt.perito",
    "pk": 20
  },
  {
    "fields": {
      "nombres": "Fernado Jose",
      "fecha_ingreso": "2007-09-05",
      "sexo": 0,
      "apellidos": "Dominguez Delgado",
      "cedula": "V-9330221"
    },
    "model": "sgt.perito",
    "pk": 21
  },
  {
    "fields": {
      "nombres": "Juana",
      "fecha_ingreso": "2011-08-17",
      "sexo": 1,
      "apellidos": "Velazquez de La Cruz",
      "cedula": "V-5432466"
    },
    "model": "sgt.perito",
    "pk": 22
  },
  {
    "fields": {
      "nombres": "Ismael Rodriguez",
      "fecha_ingreso": "2004-12-23",
      "sexo": 0,
      "apellidos": "del Valle Palacios",
      "cedula": "V-11231456"
    },
    "model": "sgt.perito",
    "pk": 23
  },
  {
    "fields": {
      "nombres": "Christian Javier ",
      "fecha_ingreso": "2012-03-29",
      "sexo": 0,
      "apellidos": "Montilla",
      "cedula": "V-11243223"
    },
    "model": "sgt.perito",
    "pk": 24
  },
  {
    "fields": {
      "nombres": "Maria Jose",
      "fecha_ingreso": "2011-02-15",
      "sexo": 1,
      "apellidos": "Perez Cardozo",
      "cedula": "V-14327765"
    },
    "model": "sgt.perito",
    "pk": 25
  },
  {
    "fields": {
      "nombres": "Juan Jose",
      "fecha_ingreso": "2010-09-14",
      "sexo": 0,
      "apellidos": "Reyes Torres",
      "cedula": "V-11234411"
    },
    "model": "sgt.perito",
    "pk": 26
  },
  {
    "fields": {
      "nombres": "Gabriela",
      "fecha_ingreso": "2012-02-15",
      "sexo": 1,
      "apellidos": "Garcia Paez",
      "cedula": "V-9449766"
    },
    "model": "sgt.perito",
    "pk": 27
  },
  {
    "fields": {
      "nombres": "Jose Miguel ",
      "fecha_ingreso": "2013-04-16",
      "sexo": 0,
      "apellidos": "Carrero Fernandez",
      "cedula": "E-20332123"
    },
    "model": "sgt.perito",
    "pk": 28
  },
  {
    "fields": {
      "nombres": "Rafael Camilo",
      "fecha_ingreso": "2011-09-16",
      "sexo": 0,
      "apellidos": "Dos Santos Rivas",
      "cedula": "V-15775321"
    },
    "model": "sgt.perito",
    "pk": 29
  },
  {
    "fields": {
      "nombres": "Juan Gabriel ",
      "fecha_ingreso": "2012-03-30",
      "sexo": 0,
      "apellidos": "Medina Castro",
      "cedula": "V-6554321"
    },
    "model": "sgt.perito",
    "pk": 30
  },
  {
    "fields": {
      "nombres": "Alejandro ",
      "fecha_ingreso": "2011-10-15",
      "sexo": 0,
      "apellidos": "Delgado Santos",
      "cedula": "V-8223456"
    },
    "model": "sgt.perito",
    "pk": 31
  },
  {
    "fields": {
      "nombres": "Fernanda Miguel",
      "fecha_ingreso": "2010-10-14",
      "sexo": 1,
      "apellidos": "Correa del Valle",
      "cedula": "V-6443211"
    },
    "model": "sgt.perito",
    "pk": 32
  },
  {
    "fields": {
      "nombres": "Carlos Miguel",
      "fecha_ingreso": "2012-08-15",
      "sexo": 0,
      "apellidos": "Correa del Valle",
      "cedula": "V-6554311"
    },
    "model": "sgt.perito",
    "pk": 33
  },
  {
    "fields": {
      "nombres": "Manuel Elías",
      "fecha_ingreso": "2010-01-14",
      "sexo": 0,
      "apellidos": "Figueroa Ramirez",
      "cedula": "V-6331124"
    },
    "model": "sgt.perito",
    "pk": 34
  },
  {
    "fields": {
      "nombres": "Antonieta ",
      "fecha_ingreso": "2010-10-13",
      "sexo": 1,
      "apellidos": "Rondon Flores",
      "cedula": "E-25664219"
    },
    "model": "sgt.perito",
    "pk": 35
  },
  {
    "fields": {
      "nombres": "Andres Eduardo",
      "fecha_ingreso": "2010-08-17",
      "sexo": 0,
      "apellidos": "Machado Mendoza",
      "cedula": "V-123457432"
    },
    "model": "sgt.perito",
    "pk": 36
  },
  {
    "fields": {
      "nombres": "Adrian ",
      "fecha_ingreso": "2011-03-16",
      "sexo": 0,
      "apellidos": "Villa Carrero",
      "cedula": "V-5655221"
    },
    "model": "sgt.perito",
    "pk": 37
  },
  {
    "fields": {
      "nombres": "Carmen Josefina",
      "fecha_ingreso": "2009-11-19",
      "sexo": 1,
      "apellidos": "Quintero Ramirez",
      "cedula": "V-13221542"
    },
    "model": "sgt.perito",
    "pk": 38
  },
  {
    "fields": {
      "nombres": "Carlos Miguel",
      "fecha_ingreso": "2013-06-12",
      "sexo": 0,
      "apellidos": "Gomez Garrido",
      "cedula": "V-7887536"
    },
    "model": "sgt.perito",
    "pk": 39
  },
  {
    "fields": {
      "nombres": "Javier Jose",
      "fecha_ingreso": "2009-11-20",
      "sexo": 0,
      "apellidos": "Maldonado",
      "cedula": "V-8766530"
    },
    "model": "sgt.perito",
    "pk": 40
  },
  {
    "fields": {
      "nombres": "Miguel Antonio",
      "fecha_ingreso": "2010-08-11",
      "sexo": 0,
      "apellidos": "Diaz Fernandez",
      "cedula": "V-11235221"
    },
    "model": "sgt.perito",
    "pk": 41
  },
  {
    "fields": {
      "nombres": "Victor Manuel",
      "fecha_ingreso": "2010-11-24",
      "sexo": 0,
      "apellidos": "Garrido Lopez",
      "cedula": "V-6559123"
    },
    "model": "sgt.perito",
    "pk": 42
  },
  {
    "fields": {
      "nombres": "Juana Cristina",
      "fecha_ingreso": "2012-06-13",
      "sexo": 1,
      "apellidos": "Machado Casanova",
      "cedula": "V-14678241"
    },
    "model": "sgt.perito",
    "pk": 43
  },
  {
    "fields": {
      "nombres": "Francisco",
      "fecha_ingreso": "2010-10-21",
      "sexo": 0,
      "apellidos": "Varela Macedo",
      "cedula": "V-12236723"
    },
    "model": "sgt.perito",
    "pk": 44
  },
  {
    "fields": {
      "nombres": "Jhonatan Guillermo",
      "fecha_ingreso": "2011-10-20",
      "sexo": 0,
      "apellidos": "Perez Suarez",
      "cedula": "V-8432625"
    },
    "model": "sgt.perito",
    "pk": 45
  },
  {
    "fields": {
      "nombres": "Carmen Elizabeth",
      "fecha_ingreso": "2009-10-21",
      "sexo": 1,
      "apellidos": "Santos Palacios",
      "cedula": "V-12446151"
    },
    "model": "sgt.perito",
    "pk": 46
  },
  {
    "fields": {
      "nombres": "Carlos Jose",
      "fecha_ingreso": "2009-08-19",
      "sexo": 1,
      "apellidos": "Reyes Dominguez",
      "cedula": "V-14665311"
    },
    "model": "sgt.perito",
    "pk": 47
  },
  {
    "fields": {
      "nombres": "Carlos Miguel",
      "fecha_ingreso": "2008-08-12",
      "sexo": 0,
      "apellidos": "del Valle Palacios",
      "cedula": "V-16245122"
    },
    "model": "sgt.perito",
    "pk": 48
  },
  {
    "fields": {
      "nombres": "Daniela Katrina",
      "fecha_ingreso": "2009-04-21",
      "sexo": 1,
      "apellidos": "Dolores Rivas",
      "cedula": "V-7883123"
    },
    "model": "sgt.perito",
    "pk": 49
  },
  {
    "fields": {
      "nombres": "Jhonatan",
      "fecha_ingreso": "2010-05-18",
      "sexo": 0,
      "apellidos": "Urdaneta Silva",
      "cedula": "V-5650021"
    },
    "model": "sgt.perito",
    "pk": 50
  },
  {
    "fields": {
      "nombres": "Leonardo ",
      "fecha_ingreso": "2011-04-28",
      "sexo": 0,
      "apellidos": "Leon Rivero",
      "cedula": "E-23222134"
    },
    "model": "sgt.perito",
    "pk": 51
  }
]